openqudit-0.2.1.dist-info/RECORD
openqudit-0.2.1.dist-info/WHEEL
openqudit-0.2.1.dist-info/METADATA
openqudit-0.2.1.dist-info/licenses/LICENSE
openqudit-0.2.1.dist-info/licenses/THIRD-PARTY-LICENSES.json
openqudit/openqudit.abi3.so
openqudit/__init__.py
