Metadata-Version: 2.4
Name: openqudit
Version: 0.2.1
Classifier: Programming Language :: Rust
Classifier: Programming Language :: Python :: Implementation :: CPython
Classifier: Programming Language :: Python :: Implementation :: PyPy
Requires-Dist: numpy>=2
License-File: LICENSE
License-File: THIRD-PARTY-LICENSES.json
License-Expression: BSD-3-Clause
Requires-Python: >=3.9
